mipas_noxy/__init__.py
mipas_noxy/__main__.py
mipas_noxy/correlate.py
mipas_noxy/util.py
mipas_noxy-0.0.1.dist-info/LICENSE
mipas_noxy-0.0.1.dist-info/METADATA
mipas_noxy-0.0.1.dist-info/WHEEL
mipas_noxy-0.0.1.dist-info/entry_points.txt
mipas_noxy-0.0.1.dist-info/top_level.txt
mipas_noxy-0.0.1.dist-info/RECORD
