Metadata-Version: 2.1
Name: mipas_noxy
Version: 0.0.1
Summary: MIPAS level-2 NOx/NOy calculater
Home-page: https://github.com/st-bender/pymipas_noxy
Author: Stefan Bender
Author-email: sbender@iaa.es
License: GPLv2
Classifier: Development Status :: 3 - Alpha
Classifier: Intended Audience :: Science/Research
Classifier: License :: OSI Approved :: GNU General Public License v2 (GPLv2)
Classifier: Programming Language :: Python
Classifier: Programming Language :: Python :: 2
Classifier: Programming Language :: Python :: 3
Classifier: Topic :: Scientific/Engineering :: Physics
Classifier: Topic :: Utilities
License-File: LICENSE
Requires-Dist: numpy
Requires-Dist: scipy
Requires-Dist: xarray
Requires-Dist: h5netcdf
Requires-Dist: click
Requires-Dist: toml
Provides-Extra: all
Requires-Dist: pytest ; extra == 'all'
Provides-Extra: tests
Requires-Dist: pytest ; extra == 'tests'
